fmf/__init__.py
fmf/__main__.py
fmf/cli.py
fmf/processes/__init__.py
fmf/processes/api.py
fmf/processes/webapp.py
fmf/utils/__init__.py
fmf/utils/version.py
forge_my_flask-0.2.0.dist-info/licenses/LICENSE
forge_my_flask-0.2.0.dist-info/METADATA
forge_my_flask-0.2.0.dist-info/WHEEL
forge_my_flask-0.2.0.dist-info/entry_points.txt
forge_my_flask-0.2.0.dist-info/top_level.txt
forge_my_flask-0.2.0.dist-info/RECORD
