Metadata-Version: 2.4
Name: forge-my-flask
Version: 0.2.0
Summary: A CLI tool to scaffold Flask web apps and APIs
Author: Sparklee
License: MIT
Project-URL: Homepage, https://github.com/Sparkleeop/Forge-my-FLASK
Project-URL: Repository, https://github.com/Sparkleeop/Forge-my-FLASK
Project-URL: Issues, https://github.com/Sparkleeop/Forge-my-FLASK/issues
Requires-Python: >=3.9
License-File: LICENSE
Requires-Dist: flask
Dynamic: license-file
